osc_transformer_based_extractor-0.1.7.dist-info/METADATA
osc_transformer_based_extractor-0.1.7.dist-info/WHEEL
osc_transformer_based_extractor-0.1.7.dist-info/entry_points.txt
osc_transformer_based_extractor-0.1.7.dist-info/licenses/LICENSE.txt
osc_transformer_based_extractor/__init__.py
osc_transformer_based_extractor/kpi_detection/__init__.py
osc_transformer_based_extractor/kpi_detection/cli_kpi_detection.py
osc_transformer_based_extractor/kpi_detection/inference_kpi_detection.py
osc_transformer_based_extractor/kpi_detection/train_kpi_detection.py
osc_transformer_based_extractor/main_cli.py
osc_transformer_based_extractor/relevance_detector/__init__.py
osc_transformer_based_extractor/relevance_detector/cli_relevance_detector.py
osc_transformer_based_extractor/relevance_detector/fine_tune.py
osc_transformer_based_extractor/relevance_detector/inference.py
osc_transformer_based_extractor-0.1.7.dist-info/RECORD
