Metadata-Version: 2.1
Name: osc-transformer-based-extractor
Version: 0.1.7
Summary: OS-Climate Data Extraction Tool
Author-Email: Tanishq More <tanishq.more@investmentdataservices.com>
License:                                  Apache License
Classifier: Intended Audience :: Developers
Classifier: Intended Audience :: Science/Research
Classifier: License :: OSI Approved :: Apache Software License
Classifier: Operating System :: MacOS
Classifier: Operating System :: Microsoft :: Windows
Classifier: Operating System :: Unix
Classifier: Programming Language :: Python
Classifier: Programming Language :: Python :: 3
Classifier: Programming Language :: Python :: 3 :: Only
Classifier: Programming Language :: Python :: 3.11
Classifier: Programming Language :: Python :: 3.10
Classifier: Programming Language :: Python :: 3.9
Classifier: Topic :: Office/Business :: Financial
Classifier: Topic :: Scientific/Engineering
Classifier: Topic :: Software Development
Project-URL: Homepage, https://github.com/os-climate/osc-transformer-based-extractor
Project-URL: Repository, https://github.com/os-climate/osc-transformer-based-extractor
Project-URL: Downloads, https://github.com/os-climate/osc-transformer-based-extractor/releases
Project-URL: Bug Tracker, https://github.com/os-climate/osc-transformer-based-extractor/issues
Project-URL: Documentation, https://github.com/os-climate/osc-transformer-based-extractor/tree/main/docs
Project-URL: Source Code, https://github.com/os-climate/osc-transformer-based-extractor
Requires-Python: >=3.9
Requires-Dist: torch>=2.6.0
Requires-Dist: pandas>=2.2.3
Requires-Dist: tokenizers>=0.21.0
Requires-Dist: transformers>=4.48.2
Requires-Dist: pre-commit>=4.1.0
Requires-Dist: pytest>=8.3.4
Requires-Dist: pytest-cov>=6.0.0
Requires-Dist: scikit-learn>=1.6.1
Requires-Dist: accelerate>=1.3.0
Requires-Dist: typer[all]>=0.15.1
Requires-Dist: rich>=13.9.4
Requires-Dist: numpy>=1.26.4
Requires-Dist: openpyxl>=3.1.5
Requires-Dist: datasets>=3.2.0
Requires-Dist: torchvision>=0.21.0
Requires-Dist: torchaudio>=2.6.0
Provides-Extra: dev
Requires-Dist: pylint; extra == "dev"
Requires-Dist: toml; extra == "dev"
Requires-Dist: yapf; extra == "dev"
Requires-Dist: pdm; extra == "dev"
Provides-Extra: test
Requires-Dist: pytest; extra == "test"
Requires-Dist: pytest-cov; extra == "test"
